backlite/__init__.py
backlite/_commands.py
backlite/_metadata.py
backlite/_migrations.py
backlite/decorators.py
backlite/py.typed
backlite/storage.py
backlite/types.py
backlite-0.0.6.dist-info/METADATA
backlite-0.0.6.dist-info/WHEEL
backlite-0.0.6.dist-info/licenses/LICENSE.txt
backlite-0.0.6.dist-info/RECORD
