Metadata-Version: 2.4
Name: backlite
Version: 0.0.6
Summary: A file-based caching library backed by SQLite.
Project-URL: Source, https://github.com/rmorshea/backlite
Author-email: Ryan Morshead <ryan.morshead@gmail.com>
License: MIT License
License-File: LICENSE.txt
Classifier: Development Status :: 4 - Beta
Classifier: Programming Language :: Python
Requires-Python: <4,>=3.11
Requires-Dist: anyio>=4.8.0
Requires-Dist: paramorator>=1.0.2
